{
 "custom_fields": [
  {
   "_assign": null,
   "_comments": null,
   "_liked_by": null,
   "_user_tags": null,
   "allow_in_quick_entry": 1,
   "allow_on_submit": 0,
   "bold": 0,
   "collapsible": 0,
   "collapsible_depends_on": null,
   "columns": 1,
   "creation": "2024-06-26 11:51:20.445980",
   "default": null,
   "depends_on": null,
   "description": null,
   "docstatus": 0,
   "dt": "Sales Invoice Item",
   "fetch_from": "item_code.custom_chassis_no",
   "fetch_if_empty": 0,
   "fieldname": "custom_chassis_",
   "fieldtype": "Data",
   "hidden": 0,
   "hide_border": 0,
   "hide_days": 0,
   "hide_seconds": 0,
   "idx": 6,
   "ignore_user_permissions": 0,
   "ignore_xss_filter": 0,
   "in_global_search": 0,
   "in_list_view": 1,
   "in_preview": 0,
   "in_standard_filter": 0,
   "insert_after": "custom_engine",
   "is_system_generated": 0,
   "is_virtual": 0,
   "label": "Chassis ",
   "length": 0,
   "link_filters": null,
   "mandatory_depends_on": null,
   "modified": "2024-06-26 11:51:20.445980",
   "modified_by": "Administrator",
   "module": null,
   "name": "Sales Invoice Item-custom_chassis_",
   "no_copy": 0,
   "non_negative": 0,
   "options": null,
   "owner": "Administrator",
   "permlevel": 0,
   "precision": "",
   "print_hide": 0,
   "print_hide_if_no_value": 0,
   "print_width": null,
   "read_only": 0,
   "read_only_depends_on": null,
   "report_hide": 0,
   "reqd": 0,
   "search_index": 0,
   "show_dashboard": 0,
   "sort_options": 0,
   "translatable": 1,
   "unique": 0,
   "width": null
  },
  {
   "_assign": null,
   "_comments": null,
   "_liked_by": null,
   "_user_tags": null,
   "allow_in_quick_entry": 1,
   "allow_on_submit": 0,
   "bold": 0,
   "collapsible": 0,
   "collapsible_depends_on": null,
   "columns": 0,
   "creation": "2024-06-26 11:51:21.285450",
   "default": null,
   "depends_on": null,
   "description": null,
   "docstatus": 0,
   "dt": "Sales Invoice Item",
   "fetch_from": "item_code.custom_color",
   "fetch_if_empty": 0,
   "fieldname": "custom_color",
   "fieldtype": "Data",
   "hidden": 0,
   "hide_border": 0,
   "hide_days": 0,
   "hide_seconds": 0,
   "idx": 15,
   "ignore_user_permissions": 0,
   "ignore_xss_filter": 0,
   "in_global_search": 0,
   "in_list_view": 0,
   "in_preview": 0,
   "in_standard_filter": 0,
   "insert_after": "custom_model",
   "is_system_generated": 0,
   "is_virtual": 0,
   "label": "Color",
   "length": 0,
   "link_filters": null,
   "mandatory_depends_on": null,
   "modified": "2024-06-26 11:51:21.285450",
   "modified_by": "Administrator",
   "module": null,
   "name": "Sales Invoice Item-custom_color",
   "no_copy": 0,
   "non_negative": 0,
   "options": null,
   "owner": "Administrator",
   "permlevel": 0,
   "precision": "",
   "print_hide": 0,
   "print_hide_if_no_value": 0,
   "print_width": null,
   "read_only": 0,
   "read_only_depends_on": null,
   "report_hide": 0,
   "reqd": 0,
   "search_index": 0,
   "show_dashboard": 0,
   "sort_options": 0,
   "translatable": 1,
   "unique": 0,
   "width": null
  },
  {
   "_assign": null,
   "_comments": null,
   "_liked_by": null,
   "_user_tags": null,
   "allow_in_quick_entry": 1,
   "allow_on_submit": 0,
   "bold": 0,
   "collapsible": 0,
   "collapsible_depends_on": null,
   "columns": 1,
   "creation": "2024-06-26 11:51:20.135781",
   "default": null,
   "depends_on": null,
   "description": null,
   "docstatus": 0,
   "dt": "Sales Invoice Item",
   "fetch_from": "item_code.custom_engine_number",
   "fetch_if_empty": 0,
   "fieldname": "custom_engine",
   "fieldtype": "Data",
   "hidden": 0,
   "hide_border": 0,
   "hide_days": 0,
   "hide_seconds": 0,
   "idx": 5,
   "ignore_user_permissions": 0,
   "ignore_xss_filter": 0,
   "in_global_search": 0,
   "in_list_view": 1,
   "in_preview": 0,
   "in_standard_filter": 0,
   "insert_after": "custom_fc_vehicle",
   "is_system_generated": 0,
   "is_virtual": 0,
   "label": "Engine",
   "length": 0,
   "link_filters": null,
   "mandatory_depends_on": null,
   "modified": "2024-06-26 11:51:20.135781",
   "modified_by": "Administrator",
   "module": null,
   "name": "Sales Invoice Item-custom_engine",
   "no_copy": 0,
   "non_negative": 0,
   "options": null,
   "owner": "Administrator",
   "permlevel": 0,
   "precision": "",
   "print_hide": 0,
   "print_hide_if_no_value": 0,
   "print_width": null,
   "read_only": 0,
   "read_only_depends_on": null,
   "report_hide": 0,
   "reqd": 0,
   "search_index": 0,
   "show_dashboard": 0,
   "sort_options": 0,
   "translatable": 1,
   "unique": 0,
   "width": null
  },
  {
   "_assign": null,
   "_comments": null,
   "_liked_by": null,
   "_user_tags": null,
   "allow_in_quick_entry": 1,
   "allow_on_submit": 0,
   "bold": 0,
   "collapsible": 0,
   "collapsible_depends_on": null,
   "columns": 1,
   "creation": "2024-06-26 11:49:17.805099",
   "default": null,
   "depends_on": null,
   "description": null,
   "docstatus": 0,
   "dt": "Sales Invoice Item",
   "fetch_from": "item_code.custom_vehicle",
   "fetch_if_empty": 0,
   "fieldname": "custom_fc_vehicle",
   "fieldtype": "Link",
   "hidden": 0,
   "hide_border": 0,
   "hide_days": 0,
   "hide_seconds": 0,
   "idx": 4,
   "ignore_user_permissions": 0,
   "ignore_xss_filter": 0,
   "in_global_search": 0,
   "in_list_view": 1,
   "in_preview": 0,
   "in_standard_filter": 0,
   "insert_after": "item_code",
   "is_system_generated": 0,
   "is_virtual": 0,
   "label": "FC Vehicle",
   "length": 0,
   "link_filters": null,
   "mandatory_depends_on": null,
   "modified": "2024-06-26 11:49:17.805099",
   "modified_by": "Administrator",
   "module": null,
   "name": "Sales Invoice Item-custom_fc_vehicle",
   "no_copy": 0,
   "non_negative": 0,
   "options": "FC Vehicle",
   "owner": "Administrator",
   "permlevel": 0,
   "precision": "",
   "print_hide": 0,
   "print_hide_if_no_value": 0,
   "print_width": null,
   "read_only": 0,
   "read_only_depends_on": null,
   "report_hide": 0,
   "reqd": 0,
   "search_index": 0,
   "show_dashboard": 0,
   "sort_options": 0,
   "translatable": 0,
   "unique": 0,
   "width": null
  },
  {
   "_assign": null,
   "_comments": null,
   "_liked_by": null,
   "_user_tags": null,
   "allow_in_quick_entry": 0,
   "allow_on_submit": 0,
   "bold": 0,
   "collapsible": 0,
   "collapsible_depends_on": null,
   "columns": 0,
   "creation": "2024-09-03 00:14:53.166097",
   "default": null,
   "depends_on": null,
   "description": null,
   "docstatus": 0,
   "dt": "Sales Invoice Item",
   "fetch_from": "item_code.custom_investor_name",
   "fetch_if_empty": 0,
   "fieldname": "custom_investor_name",
   "fieldtype": "Data",
   "hidden": 0,
   "hide_border": 0,
   "hide_days": 0,
   "hide_seconds": 0,
   "idx": 8,
   "ignore_user_permissions": 0,
   "ignore_xss_filter": 0,
   "in_global_search": 0,
   "in_list_view": 0,
   "in_preview": 0,
   "in_standard_filter": 0,
   "insert_after": "custom_mulkia",
   "is_system_generated": 0,
   "is_virtual": 0,
   "label": "Investor Name",
   "length": 0,
   "link_filters": null,
   "mandatory_depends_on": null,
   "modified": "2024-09-03 00:14:53.166097",
   "modified_by": "Administrator",
   "module": null,
   "name": "Sales Invoice Item-custom_investor_name",
   "no_copy": 0,
   "non_negative": 0,
   "options": null,
   "owner": "Administrator",
   "permlevel": 0,
   "precision": "",
   "print_hide": 0,
   "print_hide_if_no_value": 0,
   "print_width": null,
   "read_only": 0,
   "read_only_depends_on": null,
   "report_hide": 0,
   "reqd": 0,
   "search_index": 0,
   "show_dashboard": 0,
   "sort_options": 0,
   "translatable": 1,
   "unique": 0,
   "width": null
  },
  {
   "_assign": null,
   "_comments": null,
   "_liked_by": null,
   "_user_tags": null,
   "allow_in_quick_entry": 1,
   "allow_on_submit": 0,
   "bold": 0,
   "collapsible": 0,
   "collapsible_depends_on": null,
   "columns": 1,
   "creation": "2024-06-26 11:51:20.721674",
   "default": null,
   "depends_on": null,
   "description": null,
   "docstatus": 0,
   "dt": "Sales Invoice Item",
   "fetch_from": "item_code.custom_manufacture",
   "fetch_if_empty": 0,
   "fieldname": "custom_make",
   "fieldtype": "Data",
   "hidden": 0,
   "hide_border": 0,
   "hide_days": 0,
   "hide_seconds": 0,
   "idx": 13,
   "ignore_user_permissions": 0,
   "ignore_xss_filter": 0,
   "in_global_search": 0,
   "in_list_view": 1,
   "in_preview": 0,
   "in_standard_filter": 0,
   "insert_after": "customer_item_code",
   "is_system_generated": 0,
   "is_virtual": 0,
   "label": "Make",
   "length": 0,
   "link_filters": null,
   "mandatory_depends_on": null,
   "modified": "2024-06-26 11:51:20.721674",
   "modified_by": "Administrator",
   "module": null,
   "name": "Sales Invoice Item-custom_make",
   "no_copy": 0,
   "non_negative": 0,
   "options": null,
   "owner": "Administrator",
   "permlevel": 0,
   "precision": "",
   "print_hide": 0,
   "print_hide_if_no_value": 0,
   "print_width": null,
   "read_only": 0,
   "read_only_depends_on": null,
   "report_hide": 0,
   "reqd": 0,
   "search_index": 0,
   "show_dashboard": 0,
   "sort_options": 0,
   "translatable": 1,
   "unique": 0,
   "width": null
  },
  {
   "_assign": null,
   "_comments": null,
   "_liked_by": null,
   "_user_tags": null,
   "allow_in_quick_entry": 1,
   "allow_on_submit": 0,
   "bold": 0,
   "collapsible": 0,
   "collapsible_depends_on": null,
   "columns": 1,
   "creation": "2024-06-26 11:51:20.991794",
   "default": null,
   "depends_on": null,
   "description": null,
   "docstatus": 0,
   "dt": "Sales Invoice Item",
   "fetch_from": "item_code.custom_model",
   "fetch_if_empty": 0,
   "fieldname": "custom_model",
   "fieldtype": "Data",
   "hidden": 0,
   "hide_border": 0,
   "hide_days": 0,
   "hide_seconds": 0,
   "idx": 14,
   "ignore_user_permissions": 0,
   "ignore_xss_filter": 0,
   "in_global_search": 0,
   "in_list_view": 1,
   "in_preview": 0,
   "in_standard_filter": 0,
   "insert_after": "custom_make",
   "is_system_generated": 0,
   "is_virtual": 0,
   "label": "Model",
   "length": 0,
   "link_filters": null,
   "mandatory_depends_on": null,
   "modified": "2024-06-26 11:51:20.991794",
   "modified_by": "Administrator",
   "module": null,
   "name": "Sales Invoice Item-custom_model",
   "no_copy": 0,
   "non_negative": 0,
   "options": null,
   "owner": "Administrator",
   "permlevel": 0,
   "precision": "",
   "print_hide": 0,
   "print_hide_if_no_value": 0,
   "print_width": null,
   "read_only": 0,
   "read_only_depends_on": null,
   "report_hide": 0,
   "reqd": 0,
   "search_index": 0,
   "show_dashboard": 0,
   "sort_options": 0,
   "translatable": 1,
   "unique": 0,
   "width": null
  },
  {
   "_assign": null,
   "_comments": null,
   "_liked_by": null,
   "_user_tags": null,
   "allow_in_quick_entry": 0,
   "allow_on_submit": 0,
   "bold": 0,
   "collapsible": 0,
   "collapsible_depends_on": null,
   "columns": 0,
   "creation": "2024-08-09 23:55:05.691240",
   "default": null,
   "depends_on": null,
   "description": null,
   "docstatus": 0,
   "dt": "Sales Invoice Item",
   "fetch_from": "item_code.custom_mulkia_name",
   "fetch_if_empty": 0,
   "fieldname": "custom_mulkia",
   "fieldtype": "Data",
   "hidden": 0,
   "hide_border": 0,
   "hide_days": 0,
   "hide_seconds": 0,
   "idx": 7,
   "ignore_user_permissions": 0,
   "ignore_xss_filter": 0,
   "in_global_search": 0,
   "in_list_view": 0,
   "in_preview": 0,
   "in_standard_filter": 0,
   "insert_after": "custom_chassis_",
   "is_system_generated": 0,
   "is_virtual": 0,
   "label": "Mulkia",
   "length": 0,
   "link_filters": null,
   "mandatory_depends_on": null,
   "modified": "2024-08-09 23:55:05.691240",
   "modified_by": "Administrator",
   "module": null,
   "name": "Sales Invoice Item-custom_mulkia",
   "no_copy": 0,
   "non_negative": 0,
   "options": null,
   "owner": "Administrator",
   "permlevel": 0,
   "precision": "",
   "print_hide": 0,
   "print_hide_if_no_value": 0,
   "print_width": null,
   "read_only": 0,
   "read_only_depends_on": null,
   "report_hide": 0,
   "reqd": 0,
   "search_index": 0,
   "show_dashboard": 0,
   "sort_options": 0,
   "translatable": 1,
   "unique": 0,
   "width": null
  },
  {
   "_assign": null,
   "_comments": null,
   "_liked_by": null,
   "_user_tags": null,
   "allow_in_quick_entry": 1,
   "allow_on_submit": 0,
   "bold": 0,
   "collapsible": 0,
   "collapsible_depends_on": null,
   "columns": 1,
   "creation": "2024-06-26 11:51:21.583772",
   "default": null,
   "depends_on": null,
   "description": null,
   "docstatus": 0,
   "dt": "Sales Invoice Item",
   "fetch_from": "item_code.custom_licence_plate",
   "fetch_if_empty": 0,
   "fieldname": "custom_plate",
   "fieldtype": "Data",
   "hidden": 0,
   "hide_border": 0,
   "hide_days": 0,
   "hide_seconds": 0,
   "idx": 16,
   "ignore_user_permissions": 0,
   "ignore_xss_filter": 0,
   "in_global_search": 0,
   "in_list_view": 1,
   "in_preview": 0,
   "in_standard_filter": 0,
   "insert_after": "custom_color",
   "is_system_generated": 0,
   "is_virtual": 0,
   "label": "Plate",
   "length": 0,
   "link_filters": null,
   "mandatory_depends_on": null,
   "modified": "2024-06-26 11:51:21.583772",
   "modified_by": "Administrator",
   "module": null,
   "name": "Sales Invoice Item-custom_plate",
   "no_copy": 0,
   "non_negative": 0,
   "options": null,
   "owner": "Administrator",
   "permlevel": 0,
   "precision": "",
   "print_hide": 0,
   "print_hide_if_no_value": 0,
   "print_width": null,
   "read_only": 0,
   "read_only_depends_on": null,
   "report_hide": 0,
   "reqd": 0,
   "search_index": 0,
   "show_dashboard": 0,
   "sort_options": 0,
   "translatable": 1,
   "unique": 0,
   "width": null
  },
  {
   "_assign": null,
   "_comments": null,
   "_liked_by": null,
   "_user_tags": null,
   "allow_in_quick_entry": 0,
   "allow_on_submit": 0,
   "bold": 0,
   "collapsible": 0,
   "collapsible_depends_on": null,
   "columns": 0,
   "creation": "2024-08-08 21:00:15.882773",
   "default": null,
   "depends_on": null,
   "description": null,
   "docstatus": 0,
   "dt": "Sales Invoice Item",
   "fetch_from": null,
   "fetch_if_empty": 0,
   "fieldname": "delivery_date",
   "fieldtype": "Date",
   "hidden": 0,
   "hide_border": 0,
   "hide_days": 0,
   "hide_seconds": 0,
   "idx": 0,
   "ignore_user_permissions": 0,
   "ignore_xss_filter": 0,
   "in_global_search": 0,
   "in_list_view": 0,
   "in_preview": 0,
   "in_standard_filter": 0,
   "insert_after": "item_name",
   "is_system_generated": 1,
   "is_virtual": 0,
   "label": "Delivery Date",
   "length": 0,
   "link_filters": null,
   "mandatory_depends_on": null,
   "modified": "2024-08-08 21:00:46.045097",
   "modified_by": "samarth.upare@redtra.com",
   "module": null,
   "name": "Sales Invoice Item-delivery_date",
   "no_copy": 0,
   "non_negative": 0,
   "options": null,
   "owner": "Administrator",
   "permlevel": 0,
   "precision": "",
   "print_hide": 1,
   "print_hide_if_no_value": 0,
   "print_width": null,
   "read_only": 0,
   "read_only_depends_on": null,
   "report_hide": 0,
   "reqd": 0,
   "search_index": 0,
   "show_dashboard": 0,
   "sort_options": 0,
   "translatable": 0,
   "unique": 0,
   "width": null
  },
  {
   "_assign": null,
   "_comments": null,
   "_liked_by": null,
   "_user_tags": null,
   "allow_in_quick_entry": 0,
   "allow_on_submit": 0,
   "bold": 0,
   "collapsible": 0,
   "collapsible_depends_on": null,
   "columns": 0,
   "creation": "2024-08-08 21:00:15.898143",
   "default": null,
   "depends_on": null,
   "description": null,
   "docstatus": 0,
   "dt": "Sales Invoice Item",
   "fetch_from": "item_code.is_exempt",
   "fetch_if_empty": 0,
   "fieldname": "is_exempt",
   "fieldtype": "Check",
   "hidden": 0,
   "hide_border": 0,
   "hide_days": 0,
   "hide_seconds": 0,
   "idx": 0,
   "ignore_user_permissions": 0,
   "ignore_xss_filter": 0,
   "in_global_search": 0,
   "in_list_view": 0,
   "in_preview": 0,
   "in_standard_filter": 0,
   "insert_after": "is_zero_rated",
   "is_system_generated": 1,
   "is_virtual": 0,
   "label": "Is Exempt",
   "length": 0,
   "link_filters": null,
   "mandatory_depends_on": null,
   "modified": "2024-08-08 21:00:46.068372",
   "modified_by": "samarth.upare@redtra.com",
   "module": null,
   "name": "Sales Invoice Item-is_exempt",
   "no_copy": 0,
   "non_negative": 0,
   "options": null,
   "owner": "Administrator",
   "permlevel": 0,
   "precision": "",
   "print_hide": 1,
   "print_hide_if_no_value": 0,
   "print_width": null,
   "read_only": 0,
   "read_only_depends_on": null,
   "report_hide": 0,
   "reqd": 0,
   "search_index": 0,
   "show_dashboard": 0,
   "sort_options": 0,
   "translatable": 0,
   "unique": 0,
   "width": null
  },
  {
   "_assign": null,
   "_comments": null,
   "_liked_by": null,
   "_user_tags": null,
   "allow_in_quick_entry": 0,
   "allow_on_submit": 0,
   "bold": 0,
   "collapsible": 0,
   "collapsible_depends_on": null,
   "columns": 0,
   "creation": "2024-08-08 21:00:15.890269",
   "default": null,
   "depends_on": null,
   "description": null,
   "docstatus": 0,
   "dt": "Sales Invoice Item",
   "fetch_from": "item_code.is_zero_rated",
   "fetch_if_empty": 0,
   "fieldname": "is_zero_rated",
   "fieldtype": "Check",
   "hidden": 0,
   "hide_border": 0,
   "hide_days": 0,
   "hide_seconds": 0,
   "idx": 0,
   "ignore_user_permissions": 0,
   "ignore_xss_filter": 0,
   "in_global_search": 0,
   "in_list_view": 0,
   "in_preview": 0,
   "in_standard_filter": 0,
   "insert_after": "description",
   "is_system_generated": 1,
   "is_virtual": 0,
   "label": "Is Zero Rated",
   "length": 0,
   "link_filters": null,
   "mandatory_depends_on": null,
   "modified": "2024-08-08 21:00:46.056570",
   "modified_by": "samarth.upare@redtra.com",
   "module": null,
   "name": "Sales Invoice Item-is_zero_rated",
   "no_copy": 0,
   "non_negative": 0,
   "options": null,
   "owner": "Administrator",
   "permlevel": 0,
   "precision": "",
   "print_hide": 1,
   "print_hide_if_no_value": 0,
   "print_width": null,
   "read_only": 0,
   "read_only_depends_on": null,
   "report_hide": 0,
   "reqd": 0,
   "search_index": 0,
   "show_dashboard": 0,
   "sort_options": 0,
   "translatable": 0,
   "unique": 0,
   "width": null
  },
  {
   "_assign": null,
   "_comments": null,
   "_liked_by": null,
   "_user_tags": null,
   "allow_in_quick_entry": 0,
   "allow_on_submit": 0,
   "bold": 0,
   "collapsible": 0,
   "collapsible_depends_on": null,
   "columns": 0,
   "creation": "2024-08-08 21:00:15.866759",
   "default": null,
   "depends_on": null,
   "description": null,
   "docstatus": 0,
   "dt": "Sales Invoice Item",
   "fetch_from": null,
   "fetch_if_empty": 0,
   "fieldname": "tax_amount",
   "fieldtype": "Currency",
   "hidden": 1,
   "hide_border": 0,
   "hide_days": 0,
   "hide_seconds": 0,
   "idx": 0,
   "ignore_user_permissions": 0,
   "ignore_xss_filter": 0,
   "in_global_search": 0,
   "in_list_view": 0,
   "in_preview": 0,
   "in_standard_filter": 0,
   "insert_after": "tax_rate",
   "is_system_generated": 1,
   "is_virtual": 0,
   "label": "Tax Amount",
   "length": 0,
   "link_filters": null,
   "mandatory_depends_on": null,
   "modified": "2024-08-08 21:00:46.021217",
   "modified_by": "samarth.upare@redtra.com",
   "module": null,
   "name": "Sales Invoice Item-tax_amount",
   "no_copy": 0,
   "non_negative": 0,
   "options": "currency",
   "owner": "Administrator",
   "permlevel": 0,
   "precision": "",
   "print_hide": 1,
   "print_hide_if_no_value": 0,
   "print_width": null,
   "read_only": 1,
   "read_only_depends_on": null,
   "report_hide": 0,
   "reqd": 0,
   "search_index": 0,
   "show_dashboard": 0,
   "sort_options": 0,
   "translatable": 0,
   "unique": 0,
   "width": null
  },
  {
   "_assign": null,
   "_comments": null,
   "_liked_by": null,
   "_user_tags": null,
   "allow_in_quick_entry": 0,
   "allow_on_submit": 1,
   "bold": 0,
   "collapsible": 0,
   "collapsible_depends_on": null,
   "columns": 0,
   "creation": "2024-08-08 21:00:15.849945",
   "default": null,
   "depends_on": null,
   "description": null,
   "docstatus": 0,
   "dt": "Sales Invoice Item",
   "fetch_from": "item_code.tax_code",
   "fetch_if_empty": 0,
   "fieldname": "tax_code",
   "fieldtype": "Read Only",
   "hidden": 0,
   "hide_border": 0,
   "hide_days": 0,
   "hide_seconds": 0,
   "idx": 0,
   "ignore_user_permissions": 0,
   "ignore_xss_filter": 0,
   "in_global_search": 0,
   "in_list_view": 0,
   "in_preview": 0,
   "in_standard_filter": 0,
   "insert_after": "description",
   "is_system_generated": 1,
   "is_virtual": 0,
   "label": "Tax Code",
   "length": 0,
   "link_filters": null,
   "mandatory_depends_on": null,
   "modified": "2024-08-08 21:00:45.995440",
   "modified_by": "samarth.upare@redtra.com",
   "module": null,
   "name": "Sales Invoice Item-tax_code",
   "no_copy": 0,
   "non_negative": 0,
   "options": null,
   "owner": "Administrator",
   "permlevel": 0,
   "precision": "",
   "print_hide": 1,
   "print_hide_if_no_value": 0,
   "print_width": null,
   "read_only": 0,
   "read_only_depends_on": null,
   "report_hide": 0,
   "reqd": 0,
   "search_index": 0,
   "show_dashboard": 0,
   "sort_options": 0,
   "translatable": 0,
   "unique": 0,
   "width": null
  },
  {
   "_assign": null,
   "_comments": null,
   "_liked_by": null,
   "_user_tags": null,
   "allow_in_quick_entry": 0,
   "allow_on_submit": 0,
   "bold": 0,
   "collapsible": 0,
   "collapsible_depends_on": null,
   "columns": 0,
   "creation": "2024-08-08 21:00:15.858188",
   "default": null,
   "depends_on": null,
   "description": null,
   "docstatus": 0,
   "dt": "Sales Invoice Item",
   "fetch_from": null,
   "fetch_if_empty": 0,
   "fieldname": "tax_rate",
   "fieldtype": "Float",
   "hidden": 1,
   "hide_border": 0,
   "hide_days": 0,
   "hide_seconds": 0,
   "idx": 0,
   "ignore_user_permissions": 0,
   "ignore_xss_filter": 0,
   "in_global_search": 0,
   "in_list_view": 0,
   "in_preview": 0,
   "in_standard_filter": 0,
   "insert_after": "tax_code",
   "is_system_generated": 1,
   "is_virtual": 0,
   "label": "Tax Rate",
   "length": 0,
   "link_filters": null,
   "mandatory_depends_on": null,
   "modified": "2024-08-08 21:00:46.008939",
   "modified_by": "samarth.upare@redtra.com",
   "module": null,
   "name": "Sales Invoice Item-tax_rate",
   "no_copy": 0,
   "non_negative": 0,
   "options": null,
   "owner": "Administrator",
   "permlevel": 0,
   "precision": "",
   "print_hide": 1,
   "print_hide_if_no_value": 0,
   "print_width": null,
   "read_only": 1,
   "read_only_depends_on": null,
   "report_hide": 0,
   "reqd": 0,
   "search_index": 0,
   "show_dashboard": 0,
   "sort_options": 0,
   "translatable": 0,
   "unique": 0,
   "width": null
  },
  {
   "_assign": null,
   "_comments": null,
   "_liked_by": null,
   "_user_tags": null,
   "allow_in_quick_entry": 0,
   "allow_on_submit": 0,
   "bold": 0,
   "collapsible": 0,
   "collapsible_depends_on": null,
   "columns": 0,
   "creation": "2024-08-08 21:00:15.875345",
   "default": null,
   "depends_on": null,
   "description": null,
   "docstatus": 0,
   "dt": "Sales Invoice Item",
   "fetch_from": null,
   "fetch_if_empty": 0,
   "fieldname": "total_amount",
   "fieldtype": "Currency",
   "hidden": 1,
   "hide_border": 0,
   "hide_days": 0,
   "hide_seconds": 0,
   "idx": 0,
   "ignore_user_permissions": 0,
   "ignore_xss_filter": 0,
   "in_global_search": 0,
   "in_list_view": 0,
   "in_preview": 0,
   "in_standard_filter": 0,
   "insert_after": "tax_amount",
   "is_system_generated": 1,
   "is_virtual": 0,
   "label": "Total Amount",
   "length": 0,
   "link_filters": null,
   "mandatory_depends_on": null,
   "modified": "2024-08-08 21:00:46.031952",
   "modified_by": "samarth.upare@redtra.com",
   "module": null,
   "name": "Sales Invoice Item-total_amount",
   "no_copy": 0,
   "non_negative": 0,
   "options": "currency",
   "owner": "Administrator",
   "permlevel": 0,
   "precision": "",
   "print_hide": 1,
   "print_hide_if_no_value": 0,
   "print_width": null,
   "read_only": 1,
   "read_only_depends_on": null,
   "report_hide": 0,
   "reqd": 0,
   "search_index": 0,
   "show_dashboard": 0,
   "sort_options": 0,
   "translatable": 0,
   "unique": 0,
   "width": null
  }
 ],
 "custom_perms": [],
 "doctype": "Sales Invoice Item",
 "links": [],
 "property_setters": [
  {
   "_assign": null,
   "_comments": null,
   "_liked_by": null,
   "_user_tags": null,
   "creation": "2024-08-09 23:32:02.947645",
   "default_value": null,
   "doc_type": "Sales Invoice Item",
   "docstatus": 0,
   "doctype_or_field": "DocField",
   "field_name": "amount",
   "idx": 0,
   "is_system_generated": 0,
   "modified": "2024-09-10 19:17:25.288860",
   "modified_by": "Administrator",
   "module": null,
   "name": "Sales Invoice Item-amount-columns",
   "owner": "Administrator",
   "property": "columns",
   "property_type": "Int",
   "row_name": null,
   "value": "1"
  },
  {
   "_assign": null,
   "_comments": null,
   "_liked_by": null,
   "_user_tags": null,
   "creation": "2023-10-26 12:01:13.964538",
   "default_value": null,
   "doc_type": "Sales Invoice Item",
   "docstatus": 0,
   "doctype_or_field": "DocField",
   "field_name": "barcode",
   "idx": 0,
   "is_system_generated": 1,
   "modified": "2024-09-10 19:17:25.301741",
   "modified_by": "Administrator",
   "module": null,
   "name": "Sales Invoice Item-barcode-hidden",
   "owner": "Administrator",
   "property": "hidden",
   "property_type": "Check",
   "row_name": null,
   "value": "0"
  },
  {
   "_assign": null,
   "_comments": null,
   "_liked_by": null,
   "_user_tags": null,
   "creation": "2023-10-26 12:01:11.292644",
   "default_value": null,
   "doc_type": "Sales Invoice Item",
   "docstatus": 0,
   "doctype_or_field": "DocField",
   "field_name": "discount_account",
   "idx": 0,
   "is_system_generated": 0,
   "modified": "2024-09-13 23:49:35.172176",
   "modified_by": "Administrator",
   "module": null,
   "name": "Sales Invoice Item-discount_account-hidden",
   "owner": "Administrator",
   "property": "hidden",
   "property_type": "Check",
   "row_name": null,
   "value": "0"
  },
  {
   "_assign": null,
   "_comments": null,
   "_liked_by": null,
   "_user_tags": null,
   "creation": "2023-10-26 12:01:11.301039",
   "default_value": null,
   "doc_type": "Sales Invoice Item",
   "docstatus": 0,
   "doctype_or_field": "DocField",
   "field_name": "discount_account",
   "idx": 0,
   "is_system_generated": 0,
   "modified": "2024-09-10 19:17:25.326001",
   "modified_by": "Administrator",
   "module": null,
   "name": "Sales Invoice Item-discount_account-mandatory_depends_on",
   "owner": "Administrator",
   "property": "mandatory_depends_on",
   "property_type": "Code",
   "row_name": null,
   "value": ""
  },
  {
   "_assign": null,
   "_comments": null,
   "_liked_by": null,
   "_user_tags": null,
   "creation": "2024-08-09 23:37:01.006592",
   "default_value": null,
   "doc_type": "Sales Invoice Item",
   "docstatus": 0,
   "doctype_or_field": "DocField",
   "field_name": "item_code",
   "idx": 0,
   "is_system_generated": 0,
   "modified": "2024-09-10 19:17:25.338027",
   "modified_by": "Administrator",
   "module": null,
   "name": "Sales Invoice Item-item_code-columns",
   "owner": "Administrator",
   "property": "columns",
   "property_type": "Int",
   "row_name": null,
   "value": "1"
  },
  {
   "_assign": null,
   "_comments": null,
   "_liked_by": null,
   "_user_tags": null,
   "creation": "2024-08-09 23:32:02.486520",
   "default_value": null,
   "doc_type": "Sales Invoice Item",
   "docstatus": 0,
   "doctype_or_field": "DocField",
   "field_name": "item_name",
   "idx": 0,
   "is_system_generated": 0,
   "modified": "2024-09-10 19:17:25.349977",
   "modified_by": "Administrator",
   "module": null,
   "name": "Sales Invoice Item-item_name-columns",
   "owner": "Administrator",
   "property": "columns",
   "property_type": "Int",
   "row_name": null,
   "value": "2"
  },
  {
   "_assign": null,
   "_comments": null,
   "_liked_by": null,
   "_user_tags": null,
   "creation": "2024-09-12 19:05:34.204431",
   "default_value": null,
   "doc_type": "Sales Invoice Item",
   "docstatus": 0,
   "doctype_or_field": "DocType",
   "field_name": null,
   "idx": 0,
   "is_system_generated": 0,
   "modified": "2024-09-12 19:05:34.204431",
   "modified_by": "Administrator",
   "module": null,
   "name": "Sales Invoice Item-main-field_order",
   "owner": "Administrator",
   "property": "field_order",
   "property_type": "Data",
   "row_name": null,
   "value": "[\"barcode\", \"has_item_scanned\", \"item_code\", \"custom_fc_vehicle\", \"custom_engine\", \"custom_chassis_\", \"custom_mulkia\", \"custom_investor_name\", \"col_break1\", \"item_name\", \"delivery_date\", \"customer_item_code\", \"custom_make\", \"custom_model\", \"custom_color\", \"custom_plate\", \"description_section\", \"description\", \"tax_code\", \"tax_rate\", \"tax_amount\", \"total_amount\", \"is_zero_rated\", \"is_exempt\", \"item_group\", \"brand\", \"image_section\", \"image\", \"image_view\", \"quantity_and_rate\", \"qty\", \"stock_uom\", \"col_break2\", \"uom\", \"conversion_factor\", \"stock_qty\", \"section_break_17\", \"price_list_rate\", \"base_price_list_rate\", \"discount_and_margin\", \"margin_type\", \"margin_rate_or_amount\", \"rate_with_margin\", \"column_break_19\", \"discount_percentage\", \"discount_amount\", \"base_rate_with_margin\", \"section_break1\", \"rate\", \"amount\", \"item_tax_template\", \"col_break3\", \"base_rate\", \"base_amount\", \"pricing_rules\", \"stock_uom_rate\", \"is_free_item\", \"grant_commission\", \"section_break_21\", \"net_rate\", \"net_amount\", \"column_break_24\", \"base_net_rate\", \"base_net_amount\", \"drop_ship\", \"delivered_by_supplier\", \"accounting\", \"income_account\", \"is_fixed_asset\", \"asset\", \"finance_book\", \"col_break4\", \"expense_account\", \"discount_account\", \"deferred_revenue\", \"deferred_revenue_account\", \"service_stop_date\", \"enable_deferred_revenue\", \"column_break_50\", \"service_start_date\", \"service_end_date\", \"section_break_18\", \"weight_per_unit\", \"total_weight\", \"column_break_21\", \"weight_uom\", \"warehouse_and_reference\", \"warehouse\", \"target_warehouse\", \"quality_inspection\", \"pick_serial_and_batch\", \"serial_and_batch_bundle\", \"use_serial_batch_fields\", \"col_break5\", \"allow_zero_valuation_rate\", \"incoming_rate\", \"item_tax_rate\", \"actual_batch_qty\", \"actual_qty\", \"section_break_eoec\", \"serial_no\", \"column_break_ytgd\", \"batch_no\", \"edit_references\", \"sales_order\", \"so_detail\", \"sales_invoice_item\", \"column_break_74\", \"delivery_note\", \"dn_detail\", \"delivered_qty\", \"internal_transfer_section\", \"purchase_order\", \"column_break_92\", \"purchase_order_item\", \"accounting_dimensions_section\", \"cost_center\", \"dimension_col_break\", \"project\", \"section_break_54\", \"page_break\"]"
  },
  {
   "_assign": null,
   "_comments": null,
   "_liked_by": null,
   "_user_tags": null,
   "creation": "2024-08-09 23:32:02.667630",
   "default_value": null,
   "doc_type": "Sales Invoice Item",
   "docstatus": 0,
   "doctype_or_field": "DocField",
   "field_name": "qty",
   "idx": 0,
   "is_system_generated": 0,
   "modified": "2024-09-10 19:17:25.374455",
   "modified_by": "Administrator",
   "module": null,
   "name": "Sales Invoice Item-qty-columns",
   "owner": "Administrator",
   "property": "columns",
   "property_type": "Int",
   "row_name": null,
   "value": "1"
  },
  {
   "_assign": null,
   "_comments": null,
   "_liked_by": null,
   "_user_tags": null,
   "creation": "2024-08-09 23:32:02.813605",
   "default_value": null,
   "doc_type": "Sales Invoice Item",
   "docstatus": 0,
   "doctype_or_field": "DocField",
   "field_name": "rate",
   "idx": 0,
   "is_system_generated": 0,
   "modified": "2024-09-10 19:17:25.386932",
   "modified_by": "Administrator",
   "module": null,
   "name": "Sales Invoice Item-rate-columns",
   "owner": "Administrator",
   "property": "columns",
   "property_type": "Int",
   "row_name": null,
   "value": "1"
  },
  {
   "_assign": null,
   "_comments": null,
   "_liked_by": null,
   "_user_tags": null,
   "creation": "2023-10-26 12:01:14.179379",
   "default_value": null,
   "doc_type": "Sales Invoice Item",
   "docstatus": 0,
   "doctype_or_field": "DocField",
   "field_name": "target_warehouse",
   "idx": 0,
   "is_system_generated": 0,
   "modified": "2024-09-10 19:17:25.399179",
   "modified_by": "Administrator",
   "module": null,
   "name": "Sales Invoice Item-target_warehouse-hidden",
   "owner": "Administrator",
   "property": "hidden",
   "property_type": "Check",
   "row_name": null,
   "value": "1"
  }
 ],
 "sync_on_migrate": 1
}